{"state": [["wr", "wkn", "wb", "wq", "wk", "wb", "wkn", "wr"], ["wp", "wp", "wp", "wp", "wp", "wp", "wp", "wp"], [0, 0, 0, 0, 0, 0, 0, 0], [0, 0, 0, 0, 0, 0, 0, 0], [0, 0, 0, 0, 0, 0, 0, 0], [0, 0, 0, 0, 0, 0, 0, 0], ["bp", "bp", "bp", "bp", "bp", "bp", "bp", "bp"], ["br", "bkn", "bb", "bq", "bk", "bb", "bkn", "br"]], "currentPlayer": "w", "capturedByWhite": [], "capturedByBlack": [], "lastMove": 0, "whiteRookMoved": {"0": false, "7": false}, "blackRookMoved": {"0": false, "7": false}, "blackKingMoved": false, "whiteKingMoved": false}